{
  "timestamp": "2025-07-08T10:54:01.025Z",
  "source": "Smart Traffic Analysis",
  "competitorData": [
    {
      "domain": "https://the-foldie.com",
      "foundData": {},
      "allNumbers": [
        "7K",
        "7k",
        "6k",
        "1B",
        "4k",
        "0B",
        "4B",
        "4M",
        "2K",
        "16M",
        "11K",
        "9M",
        "0k",
        "19K",
        "6M",
        "67M",
        "5M",
        "4K",
        "1K",
        "3K",
        "40B",
        "9k",
        "3B",
        "8M",
        "3M",
        "22k",
        "0K",
        "9B",
        "0M",
        "95B",
        "29k",
        "5k",
        "7.K"
      ],
      "trafficRelated": []
    }
  ]
}